funcLibrary/__init__.py
funcLibrary/string_methods.py
funclibrary-0.1.1.dist-info/METADATA
funclibrary-0.1.1.dist-info/WHEEL
funclibrary-0.1.1.dist-info/top_level.txt
funclibrary-0.1.1.dist-info/RECORD
