Metadata-Version: 2.4
Name: funcLibrary
Version: 0.1.1
Summary: A simple Python string utilities library
Author-email: Ali Youseliyani <ayouseilyani@gmail.com>
License: MIT
Project-URL: Homepage, https://github.com/Aliyouseliyani/python_built_in_methods
Project-URL: Source, https://github.com/Aliyouseliyani/python_built_in_methods
Keywords: string,utilities,python
